memspector
