Metadata-Version: 1.1
Name: memspector
Version: 0.1.2
Summary: Inspect memory usage of python functions
Home-page: https://github.com/asciimoo/memspector
Author: Adam Tauber
Author-email: asciimoo@gmail.com
License: GNU Affero General Public License
Keywords: memory debugger inspector
Platform: UNKNOWN
Classifier: Development Status :: 4 - Beta
Classifier: Programming Language :: Python
Classifier: Topic :: Utilities
Classifier: Environment :: Console
Classifier: License :: OSI Approved :: GNU General Public License v3 or later (GPLv3+)
